[
    {
        "NO":"一",
        "topic":"「他的建築設計作品響譽國際，堪稱當代巨擘。」請找出這句話的錯字，並在答案輸入正確的字。",
        "hint":"一個中文字",
        "ans":"享",
        "realHint":"在逗點附近",
        "joke":"你知道雙腿屈膝之後會發生什麼事嗎？會蹲下喔！",
        "moreAns":"他的建築設計作品「享」譽國際，堪稱當代巨擘。"
    },
    {
        "NO":"二",
        "topic":"「處大國不攻小國，處大家不篡小家，強者不劫弱，貴者不傲賤，多詐者不欺愚。此必上利於天，中利於鬼，下利於人。三利，無所不利，故舉天下美名加之，謂之聖王。」此為哪家說法？",
        "hint":"兩個中文字",
        "ans":"墨家",
        "realHint":"兼愛非攻",
        "joke":"愚公臨死前召集兒子來到床邊虛弱的說：「移山…移山………」兒子：「亮晶晶？」愚公卒。",
        "moreAns":"「不攻小國」、「不篡小家」符合「非攻」之主張，可知為墨家。出自<墨子‧天志>。"
    },
    {
        "NO":"三",
        "topic":"下列「」內字音前後相同的是：(A)「簪」纓世族／浸潤之「譖」　(B)若「垤」若穴／藩籬「桎」梏　(C)財匱力「絀」／正身「黜」惡　(D)「檣」傾楫摧／稼「穡」之道。",
        "hint":"一個英文大寫字母",
        "ans":"C",
        "realHint":"簪ㄗㄢ、穡ㄙㄜˋ",
        "joke":"你知道人掛了之後會發生什麼事嗎？會停止呼吸喔！",
        "moreAns":"(A)ㄗㄢ / ㄗㄣˋ (B) ㄉ一ㄝˊ / ㄓˋ (C) ㄔㄨˋ (D)ㄑㄧㄤˊ / ㄙㄜˋ"
    },
    {
        "NO":"四",
        "topic":"「我撐傘走過老樹下／已不見它那灰白蒼老的影子／年輕的翠綠承受細雨的彈珠／調皮的□□在傘上（陳秀喜〈復活〉）」請從「流瀉」、「丟擲」、「沖刷」、「吞沒」裡選擇一個詞語填入□□中。",
        "hint":"兩個中文字",
        "ans":"丟擲",
        "realHint":"注意形容詞",
        "joke":"你蒸蚌，好吃嗎？",
        "moreAns":"因有調皮之意,「丟擲」更比「流瀉」能呈現調皮。"
    }
]